Xclient/__init__.py
Xclient/asyncio_utils.py
Xclient/client.py
Xclient/constants.py
Xclient/embeddings.py
Xclient/exceptions.py
Xclient/llms.py
Xclient/reranking.py
Xclient/utils.py
Xclient/version.py
Xclient/warnings.py
Xclient/model_config/__init__.py
Xclient/model_config/common.py
Xclient/model_config/generator.py
Xclient/model_config/model_config.py
Xclient/model_config/parser.py
Xclient/model_config/tensor.py
Xclient/model_config/triton_model_config.py
xuelang_Xclient-0.0.9.dist-info/LICENSE
xuelang_Xclient-0.0.9.dist-info/METADATA
xuelang_Xclient-0.0.9.dist-info/WHEEL
xuelang_Xclient-0.0.9.dist-info/top_level.txt
xuelang_Xclient-0.0.9.dist-info/RECORD
